{
  "Python Lambda Function": {
    "prefix": "lambda-psycopg",
    "body": [
      "import json",
      "from PIL import Image",
      "import io",
      "",
      "def lambda_handler(event, context):",
      "    try:",
      "        # Process image from S3",
      "        if 'Records' in event:",
      "            bucket = event['Records'][0]['s3']['bucket']['name']",
      "            key = event['Records'][0]['s3']['object']['key']",
      "            ",
      "            # Your image processing code here",
      "            img = Image.new('RGB', (100, 100), color='red')",
      "            ",
      "            return {",
      "                'statusCode': 200,",
      "                'body': json.dumps('Image processed successfully!')",
      "            }",
      "    except Exception as e:",
      "        return {",
      "            'statusCode': 500,",
      "            'body': json.dumps(f'Error: {str(e)}')",
      "        }"
    ],
    "description": "AWS Lambda function template with Psycopg"
  },
  "Psycopg Image Test": {
    "prefix": "psycopg-test",
    "body": [
      "import sys",
      "import os",
      "sys.path.insert(0, 'build/python')",
      "",
      "try:",
      "    from PIL import Image",
      "    print('✅ Psycopg import successful')",
      "    ",
      "    # Test basic functionality",
      "    img = Image.new('RGB', (100, 100), color='red')",
      "    print('✅ Image creation successful')",
      "    ",
      "    # Test format support",
      "    formats = ['JPEG', 'PNG', 'GIF', 'WEBP']",
      "    for fmt in formats:",
      "        if fmt in Image.registered_extensions().values():",
      "            print(f'✅ {fmt} format supported')",
      "        else:",
      "            print(f'❌ {fmt} format not supported')",
      "    ",
      "    print('✅ All tests passed!')",
      "    ",
      "except Exception as e:",
      "    print(f'❌ Test failed: {e}')",
      "    sys.exit(1)"
    ],
    "description": "Psycopg layer test template"
  },
  "Build Script Template": {
    "prefix": "build-script",
    "body": [
      "#!/bin/bash",
      "set -e",
      "",
      "echo \"Building Psycopg Lambda Layer...\"",
      "",
      "# Clean previous builds",
      "rm -rf build/",
      "mkdir -p build/python",
      "",
      "# Install Psycopg and dependencies",
      "pip install -r requirements.txt -t build/python/",
      "",
      "# Remove unnecessary files to reduce layer size",
      "find build/python -type d -name \"__pycache__\" -exec rm -rf {} + 2>/dev/null || true",
      "find build/python -name \"*.pyc\" -delete",
      "find build/python -name \"*.pyo\" -delete",
      "find build/python -name \"*.pyd\" -delete",
      "find build/python -name \"*.so\" -exec strip {} + 2>/dev/null || true",
      "",
      "# Remove test files and documentation",
      "find build/python -name \"test*\" -type f -delete",
      "find build/python -name \"tests\" -type d -exec rm -rf {} + 2>/dev/null || true",
      "find build/python -name \"*.md\" -delete",
      "find build/python -name \"*.txt\" -not -name \"requirements.txt\" -delete",
      "",
      "# Create layer zip",
      "cd build",
      "zip -r psycopg-layer.zip python/",
      "cd ..",
      "",
      "echo \"Layer built successfully: build/psycopg-layer.zip\"",
      "echo \"Layer size: $(du -h build/psycopg-layer.zip | cut -f1)\""
    ],
    "description": "Build script template for Psycopg layer"
  },
  "GitHub Actions Workflow": {
    "prefix": "gha-workflow",
    "body": [
      "name: Psycopg Lambda Layer CI",
      "",
      "on:",
      "  push:",
      "    branches: [main]",
      "  pull_request:",
      "    branches: [main]",
      "",
      "jobs:",
      "  build-and-test:",
      "    runs-on: ubuntu-latest",
      "    name: Build and Test Python ${{ matrix.python-version }}",
      "    permissions:",
      "      contents: read",
      "      actions: write",
      "    strategy:",
      "      matrix:",
      "        python-version: [\"3.9\", \"3.10\", \"3.11\", \"3.12\", \"3.13\"]",
      "",
      "    steps:",
      "      - name: Checkout code",
      "        uses: actions/checkout@v5",
      "",
      "      - name: Set up Python ${{ matrix.python-version }}",
      "        uses: actions/setup-python@v6",
      "        with:",
      "          python-version: ${{ matrix.python-version }}",
      "",
      "      - name: Install system dependencies",
      "        run: |",
      "          sudo apt-get update",
      "          sudo apt-get install -y \\",
      "            gcc g++ make zlib1g-dev libjpeg-dev libpng-dev \\",
      "            libtiff-dev libwebp-dev libfreetype6-dev liblcms2-dev \\",
      "            libffi-dev libopenjp2-7-dev libharfbuzz-dev libfribidi-dev \\",
      "            libxcb1-dev",
      "",
      "      - name: Build Psycopg layer",
      "        run: |",
      "          chmod +x scripts/*.sh",
      "          ./scripts/build.sh",
      "",
      "      - name: Test Psycopg layer",
      "        run: |",
      "          ./scripts/test.sh",
      "",
      "      - name: Upload layer artifact",
      "        uses: actions/upload-artifact@v4",
      "        with:",
      "          name: psycopg-layer-python${{ matrix.python-version }}",
      "          path: build/psycopg-layer.zip"
    ],
    "description": "GitHub Actions workflow template"
  }
}
